privatefields/__init__.py
privatefields/__updatedSystem__.py
PyPrivate-0.3.dist-info/LICENSE
PyPrivate-0.3.dist-info/METADATA
PyPrivate-0.3.dist-info/WHEEL
PyPrivate-0.3.dist-info/top_level.txt
PyPrivate-0.3.dist-info/RECORD
