Metadata-Version: 2.1
Name: PyPrivate
Version: 0.3
Summary: Add private/protected/public fields to Python
Home-page: https://github.com/Hyppoprogramm/PyPrivate
Author: Hyppoprogramm
Author-email: programm.jeremiah@yandex.ru
License: UNKNOWN
Project-URL: Bug Tracker, https://github.com/Hyppoprogramm/PyPrivate/issues
Platform: UNKNOWN
Classifier: Programming Language :: Python :: 3
Classifier: License :: OSI Approved :: MIT License
Classifier: Operating System :: OS Independent
Requires-Python: >=3.9
